Metadata-Version: 2.1
Name: christmascardify
Version: 0.0.2
Summary: Automate your christmas card creation!
Home-page: https://github.com/grokwithrahul/christmas-card-creator
Author: Rahul Prabhu
Author-email: rahul@grokwithrahul.com
License: UNKNOWN
Platform: UNKNOWN
